{"OL9688430W": {"goodreads": "4075153", "isbn_10": "087263311X", "isbn_13": "9780872633117", "title": "Machine Controls", "number_of_pages": 96, "publish_date": "December 1988", "subjects": ["Technology & Industrial Arts", "Automation"]}, "OL9600248W": {"isbn_10": "0811405214", "isbn_13": "9780811405218", "title": "Writing on (Teachers Edition)", "publish_date": "October 1984", "subjects": []}, "OL9600849W": {"goodreads": "3213514", "isbn_10": "0811861805", "isbn_13": "9780811861809", "title": "Paul Frank", "number_of_pages": 96, "publish_date": "March 26, 2008", "covers": [2647382], "subjects": ["Art & Art Instruction", "Art / Design / General", "Art", "Stationery items", "Design - General"]}, "OL9600981W": {"goodreads": "6470170", "isbn_10": "0811905810", "isbn_13": "9780811905817", "title": "Aram Khachaturian", "publish_date": "December 1984", "subjects": ["Music Of The 20th Century"]}, "OL9602055W": {"isbn_10": "0897745272", "isbn_13": "9780897745277", "title": "Science and Technology Annual Reference Review, 1990", "number_of_pages": 360, "publish_date": "January 1990", "covers": [5119470], "subjects": ["Science/Mathematics", "Technology: General Issues", "Reference", "Science: General Issues", "Technology & Industrial Arts"]}, "OL9602375W": {"isbn_10": "089791547X", "isbn_13": "9780897915472", "title": "Proceedings of the Acm Conference on Hypertext Miliano", "number_of_pages": 297, "publish_date": "December 1992", "covers": [13311146], "subjects": ["Science/Mathematics"]}, "OL9602455W": {"isbn_10": "0897970640", "isbn_13": "9780897970648", "title": "Jeannette Leroy", "number_of_pages": 11, "publish_date": "1990", "subjects": ["Exhibitions", "Leroy, Jeannette"]}, "OL9602782W": {"isbn_10": "0898350050", "isbn_13": "9780898350050", "title": "The Illustrated Bartsch", "publish_date": "March 1, 1979", "subjects": ["Art  / Fine Arts", "Art"]}, "OL9603062W": {"goodreads": "5701300", "isbn_10": "0898600316", "isbn_13": "9780898600315", "title": "Davis Brody and Associates", "publish_date": "November 1979", "subjects": ["Architecture"]}, "OL9603147W": {"goodreads": "2567093", "isbn_10": "0898693055", "isbn_13": "9780898693058", "title": "The Rite Light", "publish_date": "May 2000", "covers": [2682428], "subjects": ["Texts", "Church year meditations", "Religion - Christian Life", "Religion", "General", "Liturgy", "Episcopal Church"]}, "OL9603234W": {"goodreads": "7338227", "isbn_10": "0898756111", "isbn_13": "9780898756111", "title": "Soviet Medicine in the Fight Against Mental Diseases", "number_of_pages": 168, "publish_date": "September 2001", "covers": [2682536], "subjects": ["Psychology", "Medical", "Psychiatry - General", "History of ideas, intellectual history", "Psychiatry", "History", "Medical / Nursing"]}, "OL9603624W": {"goodreads": "4118315", "isbn_10": "0899065252", "isbn_13": "9780899065250", "title": "Reb Yitzchak's Jewel", "number_of_pages": 28, "publish_date": "May 1988", "subjects": ["Fiction", "Children's Books/Ages 4-8 Nonfiction", "Folklore & Mythology"]}, "OL9603719W": {"goodreads": "4353477", "isbn_10": "0899082858", "isbn_13": "9780899082851", "title": "Three Centuries of Debate on the Death Penalty", "publish_date": "September 1991", "subjects": ["Sociology", "Reference", "Criminology"]}, "OL9603863W": {"isbn_10": "0899240836", "isbn_13": "9780899240831", "title": "The Widow's Boy", "publish_date": "March 1992", "subjects": ["Popular American Fiction", "Fiction"]}, "OL9604097W": {"goodreads": "601215", "isbn_10": "0899451756", "isbn_13": "9780899451756", "title": "Let's do the write thing", "number_of_pages": 62, "publish_date": "1991", "subjects": ["Academic writing", "Composition and exercises", "Rhetoric", "English language"]}, "OL9604556W": {"goodreads": "2976523", "isbn_10": "089970459X", "isbn_13": "9780899704593", "title": "Trends in U. S. Health Care, 1992", "publish_date": "August 1992", "subjects": ["Social welfare & social services", "Health systems & services", "USA", "Health Care Policy", "Health/Fitness", "Public health & preventive medicine"]}, "OL9605244W": {"isbn_10": "0900323515", "isbn_13": "9780900323515", "title": "Code of Practice No. 19", "number_of_pages": 24, "publish_date": "February 1982", "subjects": ["Technology & Industrial Arts", "Power Resources"]}, "OL9605818W": {"isbn_10": "0900873507", "isbn_13": "9780900873508", "title": "The Price Guide to Photographic Cards", "number_of_pages": 132, "publish_date": "November 1985", "subjects": ["Criticism", "Photography", "Antiques & collectables: books, manuscripts, ephemera & printed matter"]}, "OL9606650W": {"goodreads": "4811613", "isbn_10": "0812922883", "isbn_13": "9780812922882", "title": "New York Times Guide to Mutual", "publish_date": "June 22, 1993", "subjects": ["Nonfiction - General", "Non-Classifiable"]}, "OL9606653W": {"isbn_10": "0812923316", "isbn_13": "9780812923315", "title": "Sportsbuff Sports Trivia Crossword Puzzles", "publish_date": "April 1994", "subjects": ["Games/Puzzles", "Games / Gamebooks / Crosswords", "Crosswords - General"]}, "OL9607148W": {"goodreads": "4748504", "isbn_10": "0813608139", "isbn_13": "9780813608136", "title": "Night and Day", "number_of_pages": 16, "publish_date": "December 1987", "covers": [10014036], "subjects": ["Juvenile Nonfiction", "Children: Kindergarten", "Readers - Chapter Books"]}, "OL9608523W": {"isbn_10": "0815110723", "isbn_13": "9780815110729", "title": "Multiple System Trauma Workbook (CASE STUDIES IN EMERGENCY NURSING)", "number_of_pages": 42, "publish_date": "1996", "subjects": ["Nursing - Emergency", "Medical / Nursing", "Trauma & shock"]}, "OL9608619W": {"isbn_10": "0815120036", "isbn_13": "9780815120032", "title": "Clark's Clinical Dentistry, 3 (Clark's Clinical Dentistry)", "publish_date": "August 1996", "subjects": ["Dentistry - General", "Medical / Nursing"]}, "OL9608746W": {"isbn_10": "0815140452", "isbn_13": "9780815140450", "title": "Pre- and Post-Operative Care of the Urologic Patient", "publish_date": "October 1991", "subjects": ["Medical / Nursing", "Urology"]}, "OL9608880W": {"isbn_10": "0815157797", "isbn_13": "9780815157793", "title": "The open fracture", "number_of_pages": 106, "publish_date": "1978", "subjects": ["Fractures, Open"]}, "OL9608909W": {"goodreads": "1635335", "isbn_10": "0815159757", "isbn_13": "9780815159759", "title": "Interactive Lab Practical (CLINICAL ANATOMY STUDY SYSTEM (C L A S S ))", "publish_date": "1995", "subjects": ["Anatomy"]}, "OL9609400W": {"isbn_10": "0815316577", "isbn_13": "9780815316572", "title": "The Theatre of the Absurdism", "publish_date": "February 1997", "subjects": ["Plays", "The Arts"]}, "OL9609516W": {"isbn_10": "0815338287", "isbn_13": "9780815338284", "title": "Chilean Novel in Exile", "subjects": ["Literary Criticism & Collections / General", "General", "Literature - Classics / Criticism"]}, "OL9609551W": {"isbn_10": "081540008X", "isbn_13": "9780815400080", "title": "Social Ecology, a Critical Analysis", "number_of_pages": 282, "publish_date": "June 1938", "subjects": ["Anthropology", "Human geography", "Applied ecology"]}, "OL9610281W": {"goodreads": "3924390", "isbn_10": "0816108323", "isbn_13": "9780816108329", "title": "Catalog Gaelic Manuscripts Sel", "publish_date": "July 2, 1973", "subjects": []}, "OL9611467W": {"isbn_10": "0902594435", "isbn_13": "9780902594432", "title": "The Process of Innovation", "number_of_pages": 164, "publish_date": "December 1985", "covers": [14331540], "subjects": ["Organization Of Industrial Production"]}, "OL9611715W": {"isbn_10": "0902859951", "isbn_13": "9780902859951", "title": "Dry Stone Days", "number_of_pages": 72, "publish_date": "December 1988", "covers": [11622985], "subjects": ["Modern fiction"]}, "OL9613935W": {"isbn_10": "0905927397", "isbn_13": "9780905927398", "title": "Lead in Soil", "number_of_pages": 138, "publish_date": "April 1, 1993", "subjects": ["Science/Mathematics", "Soil Science", "Science / Environmental Science", "Science", "Earth Sciences - Geology", "Soil science, sedimentology"]}, "OL9613984W": {"isbn_10": "0905958527", "isbn_13": "9780905958521", "title": "Fifty Years of Phenytoin", "number_of_pages": 32, "publish_date": "November 1987", "subjects": ["Phenytoin", "Chemotherapy", "drug therapy", "Congresses", "Epilepsy", "Health/Fitness", "therapeutic use"]}, "OL9614121W": {"isbn_10": "0906090415", "isbn_13": "9780906090411", "title": "Crop Husbandry Regimes", "number_of_pages": 227, "publish_date": "June 1992", "subjects": ["History: World", "North & North East England", "Agriculture & Farming", "BCE to c 500 CE", "History - General History", "History", "General", "Environmental archaeology"]}, "OL9614199W": {"isbn_10": "0906212626", "isbn_13": "9780906212622", "title": "Classroom Display", "number_of_pages": 96, "publish_date": "February 1991", "subjects": ["Education / Teaching", "Teaching Methods & Materials - Classroom Planning", "Teaching skills & techniques"]}, "OL9614721W": {"isbn_10": "0906602963", "isbn_13": "9780906602966", "title": "The Irish Community in the Basque Country, C. 1700-1800", "number_of_pages": 114, "publish_date": "January 2003", "subjects": ["Sociology", "Sociology, Social Studies", "Anthropology - Cultural"]}, "OL9614822W": {"goodreads": "4669335", "isbn_10": "0906630150", "isbn_13": "9780906630150", "title": "The Money Jar", "number_of_pages": 40, "publish_date": "January 2002", "subjects": ["Ireland", "American - General", "Poetry", "Coins, banknotes, medals, seals, numismatics"]}, "OL9616963W": {"goodreads": "5029853", "isbn_10": "0909605238", "isbn_13": "9780909605230", "title": "Livestock Management in the Arid Zone", "number_of_pages": 271, "publish_date": "June 1981", "subjects": ["Science/Mathematics"]}, "OL9617199W": {"isbn_10": "0910170053", "isbn_13": "9780910170055", "title": "Data processing systems used in educational institutions during 1977", "number_of_pages": 339, "publish_date": "1977", "subjects": ["Data processing", "Education"]}, "OL9617264W": {"goodreads": "72079", "isbn_10": "0910224218", "isbn_13": "9780910224215", "title": "Interactive Q&a Medical Technology Board Examination Review", "publish_date": "1996", "subjects": ["Allied Health Services - Medical Technology"]}, "OL9617811W": {"goodreads": "3025370", "isbn_10": "0910707839", "isbn_13": "9780910707831", "title": "Teen Success", "number_of_pages": 240, "publish_date": "November 1, 2007", "covers": [2684741], "subjects": ["Juvenile Nonfiction", "Beauty & Grooming - General", "Time Management", "Fashion & Grooming", "General", "Study Skills", "Children: Young Adult (Gr. 7-9)", "Nonfiction / Education"]}, "OL9619598W": {"isbn_10": "0818643005", "isbn_13": "9780818643002", "title": "Rapid System Prototyping, 4th International Workshop (Rsp '93)", "number_of_pages": 256, "publish_date": "December 1993", "subjects": ["Computer Bks - General Information", "Computers - General Information", "Electronics & Communications Engineering", "General", "Computer Programming", "Computers"]}, "OL9620745W": {"goodreads": "5878760", "isbn_10": "0819430811", "isbn_13": "9780819430816", "title": "Laser Resonators II", "number_of_pages": 354, "publish_date": "May 1999", "covers": [5480972, 5128795], "subjects": ["Lasers", "Science/Mathematics", "Technology", "Laser technology"]}, "OL9621291W": {"goodreads": "6327656", "isbn_10": "0820329185", "isbn_13": "9780820329185", "title": "Good Observers of Nature", "number_of_pages": 224, "publish_date": "July 15, 2007", "covers": [2652359], "subjects": ["Women naturalists", "Outdoors & Nature / General", "Literary Criticism", "Women Authors", "19th century", "United States", "c 1800 to c 1900", "Women botanists", "Women's studies", "English", "USA", "General", "History", "Natural history", "Literary studies: 19th century", "American - General", "Literature - Classics / Criticism", "NATURAL HISTORY, COUNTRY LIFE & PETS"]}, "OL9621735W": {"goodreads": "2185403", "isbn_10": "082044958X", "isbn_13": "9780820449586", "title": "Heinrich von Kleist ", "number_of_pages": 145, "publish_date": "June 2003", "covers": [5128889], "subjects": ["Literature: Classics", "Literary Collections", "General", "Criticism and interpretation", "Kleist, Heinrich von", "European - German", "Literature - Classics / Criticism"]}, "OL9622194W": {"isbn_10": "0820465550", "isbn_13": "9780820465555", "title": "Anti-catholic Strategies In Eighteenth-century Scotland (Scottish Studies International, V. 35)", "number_of_pages": 227, "publish_date": "October 2004", "subjects": ["Education / Teaching", "Sociology", "18th century", "Education", "General", "Sociology of Religion", "Scotland", "History", "Anti-Catholicism", "Social Science"]}, "OL9623268W": {"isbn_10": "0911389032", "isbn_13": "9780911389036", "title": "Guide to kosher eating and accommodation in North America", "number_of_pages": 208, "publish_date": "1990", "subjects": ["Directories", "Kosher food", "Hotels, taverns, etc", "Kosher restaurants", "North America"]}, "OL9623564W": {"goodreads": "4903197", "isbn_10": "0911712798", "isbn_13": "9780911712797", "title": "Physician's electro-diagnostic handbook", "publish_date": "1983", "subjects": ["Electroacupuncture", "Acupuncture", "Handbooks, manuals, etc"]}, "OL9623641W": {"goodreads": "7214863", "isbn_10": "0911790144", "isbn_13": "9780911790146", "title": "Progressive Grocer's 1994 Marketing Guidebook/the Book of Supermarket Distribution Facts/Book and Map (Marketing Guidebook)", "publish_date": "September 1993", "subjects": ["Special Business Operations", "Food And Beverage Industries (Economic Aspects)", "Business/Economics"]}, "OL9623752W": {"isbn_10": "0911866124", "title": "First Things First", "number_of_pages": 85, "publish_date": "1997", "covers": [13635443], "subjects": ["Religion & Spirituality - Christianity"]}, "OL9625053W": {"isbn_10": "0912879963", "isbn_13": "9780912879963", "title": "Why Managers Have Trouble Empowering", "publish_date": "February 1993", "covers": [2685097], "subjects": ["Management - General", "Business / Economics / Finance"]}, "OL9625501W": {"goodreads": "4114469", "isbn_10": "0913277193", "isbn_13": "9780913277195", "title": "Four O'Clock Tunes", "publish_date": "June 1986", "covers": [2685166], "subjects": ["Music", "Children: Grades 2-3", "Music/Songbooks", "Musical Instruments - Piano", "Instruction & Study - General"]}, "OL9625569W": {"goodreads": "4294017", "isbn_10": "0913321451", "isbn_13": "9780913321454", "title": "The Crumbling of the Cross", "number_of_pages": 183, "publish_date": "January 1997", "covers": [2685171], "subjects": ["Islam - General", "Religion - World Religions", "Religion", "Biblical Criticism & Interpretation - General"]}, "OL9625694W": {"goodreads": "5981804", "amazon": "", "isbn_10": "0913441171", "title": "More Than a Dream: More Than a Dream", "publish_date": "1993", "covers": [11682466], "subjects": []}, "OL9626031W": {"isbn_10": "0913719781", "isbn_13": "9780913719787", "title": "Dark With Stars", "publish_date": "June 1984", "subjects": []}, "OL9626495W": {"goodreads": "521108", "isbn_10": "0914224344", "isbn_13": "9780914224341", "title": "Good Samaritans of Death Valley", "number_of_pages": 104, "publish_date": "January 2005", "subjects": ["General", "Biography / Autobiography"]}, "OL9626540W": {"isbn_10": "0914256092", "isbn_13": "9780914256090", "title": "Real Estate the Most Successful Real Estate Listing and Selling", "publish_date": "June 1979", "subjects": []}, "OL9627529W": {"isbn_10": "0915097052", "isbn_13": "9780915097050", "title": "How to Repair Your Own Compaq Portable PC", "publish_date": "June 1985", "subjects": []}, "OL9627884W": {"isbn_10": "091539801X", "isbn_13": "9780915398010", "title": "Fold and Cut Surprise Sermonetes No Two", "publish_date": "June 1968", "subjects": []}, "OL9628055W": {"isbn_10": "091551687X", "isbn_13": "9780915516872", "title": "Rig-Color Program", "publish_date": "March 1997", "subjects": ["Sports & Recreation", "Air Sports"]}, "OL9629030W": {"isbn_10": "0821713701", "isbn_13": "9780821713709", "title": "Dynasty of Dreams", "publish_date": "May 1, 1984", "covers": [8282938], "subjects": ["Fiction"]}, "OL9629132W": {"goodreads": "3619571", "isbn_10": "0821720066", "isbn_13": "9780821720066", "title": "Love Song on a Chinese Flute", "number_of_pages": 560, "publish_date": "March 1, 1987", "covers": [14492836], "subjects": ["Fiction - General", "General", "Fiction"]}, "OL9629399W": {"isbn_10": "0821750747", "isbn_13": "9780821750742", "title": "LATE BLOOMER", "number_of_pages": 416, "publish_date": "December 1, 1999", "subjects": []}, "OL9629377W": {"isbn_10": "0821751522", "isbn_13": "9780821751527", "title": "RAVEN'S BLOOD", "number_of_pages": 224, "publish_date": "March 1, 1996", "subjects": ["Mystery & Detective - Women Sleuths", "Fiction - Mystery/ Detective"]}, "OL9629695W": {"isbn_10": "0821830163", "isbn_13": "9780821830161", "title": "Mathematical Value Problems of Mathematical Physics", "number_of_pages": 245, "publish_date": "December 1973", "covers": [5133544], "subjects": []}, "OL9630108W": {"goodreads": "3262698", "isbn_10": "082233187X", "isbn_13": "9780822331872", "title": "Gender and National Literature", "number_of_pages": 280, "publish_date": "January 2004", "covers": [5134267], "subjects": ["To 1500", "Literary studies: classical, early & medieval", "Gender Studies/Feminist Theory", "Heian period, 794-1185", "History and criticism", "Asian - Japanese", "Women authors", "Literary Criticism", "Asian - General", "Japanese literature", "Asia - General", "Literary Studies/Asian Literat", "Japan", "History", "Japanese", "Feminism and literature", "Asian Studies", "Literature - Classics / Criticism"]}, "OL9630148W": {"goodreads": "384987", "isbn_10": "0822365162", "isbn_13": "9780822365167", "title": "Queer Tourism", "number_of_pages": 258, "publish_date": "December 2002", "covers": [2654530], "subjects": ["Gay & Lesbian Studies/Queer Th", "Gay Studies", "General", "Tourism industry", "Sociology", "Gay & Lesbian studies", "Social Science"]}, "OL9630456W": {"isbn_10": "0822462818", "isbn_13": "9780822462811", "title": "Earth Science", "publish_date": "June 1987", "subjects": []}, "OL9630594W": {"goodreads": "871385", "isbn_10": "0822520516", "isbn_13": "9780822520511", "title": "The Key to Gothic Art (Key to Arts Books)", "number_of_pages": 80, "publish_date": "March 1990", "covers": [7098103], "subjects": ["Themes, motives", "Art appreciation", "Art - History", "Fine Arts (Young Adult)", "Children: Young Adult (Gr. 7-9)", "Children's Books/Young Adult Misc. Nonfiction", "Art, Gothic"]}, "OL9630950W": {"goodreads": "5642557", "isbn_10": "0823200906", "isbn_13": "9780823200900", "title": "The Publishing History of the Aristotle", "number_of_pages": 36, "publish_date": "January 1, 1978", "subjects": ["THOMAS, AQUINAS, SAINT, 1225?-1274", "Religion / Theology"]}, "OL9631265W": {"isbn_10": "0824023218", "isbn_13": "9780824023218", "title": "SOCIOLOGY OF EMOTIONS", "number_of_pages": 243, "publish_date": "January 1, 1994", "subjects": ["Sociology (Specific Aspects)", "Bibliographies & Indexes", "Education", "Reference", "Sociology"]}, "OL9631344W": {"isbn_10": "0824029429", "isbn_13": "9780824029425", "title": "FERNAND CORTE CO 2V", "publish_date": "March 1, 1979", "subjects": []}, "OL9631388W": {"goodreads": "1022199", "isbn_10": "0824042360", "isbn_13": "9780824042363", "title": "Sound & the Fury (William Faulkner Annotations)", "publish_date": "December 1996", "subjects": ["20th Century American Novel And Short Story", "English", "The Arts", "USA"]}, "OL9631636W": {"isbn_10": "0824099907", "isbn_13": "9780824099909", "title": "PETRO INDUS WEST EURO", "publish_date": "January 1, 1976", "subjects": []}, "OL9631748W": {"goodreads": "4425048", "isbn_10": "0824315375", "isbn_13": "9780824315375", "title": "Annual Review of Nuclear and Particle Science", "publish_date": "December 1987", "subjects": ["Science/Mathematics", "Nuclear Physics", "PHYSICS", "Science", "Particle Physics"]}, "OL9631970W": {"isbn_10": "0824780906", "isbn_13": "9780824780906", "title": "Capsule Technology (Drugs & the Pharmaceutical Sciences)", "publish_date": "December 15, 2006", "subjects": ["Pharmacology", "Science", "Biotechnology", "Reference", "Pharmaceutical Biotechnology Products"]}, "OL9632158W": {"isbn_10": "0915766523", "isbn_13": "9780915766529", "title": "Fractions (Dr Wise Arith)", "publish_date": "November 1981", "subjects": []}, "OL9632248W": {"goodreads": "1824080", "isbn_10": "0915866250", "title": "American Catholic Hymnbook", "publish_date": "1995", "subjects": []}, "OL9632290W": {"goodreads": "809437", "isbn_10": "0915905981", "isbn_13": "9780915905980", "title": "Negotiate! Manage! Survive! Hostage situations", "number_of_pages": 134, "publish_date": "1999", "subjects": ["Hostages", "Terrorists"]}, "OL9633575W": {"isbn_10": "0916896455", "isbn_13": "9780916896454", "title": "Standard Work on Cutting", "publish_date": "February 1993", "subjects": []}, "OL9634792W": {"isbn_10": "0918451310", "isbn_13": "9780918451316", "title": "Engineering Softwhere (Softwhere Software Directories)", "publish_date": "June 1985", "subjects": ["Technology (General)"]}, "OL9634797W": {"isbn_10": "0918451515", "isbn_13": "9780918451514", "title": "The Moore Software Register/Insurance", "publish_date": "May 1985", "subjects": []}, "OL9635199W": {"isbn_10": "0918932696", "isbn_13": "9780918932693", "title": "Focus on Fractions", "publish_date": "June 1977", "subjects": []}, "OL9635418W": {"isbn_10": "0919216765", "isbn_13": "9780919216761", "title": "Geochemistry of Sediments and Sedimentary Rocks", "number_of_pages": 184, "publish_date": "September 2003", "covers": [5137253], "subjects": ["Science/Mathematics", "Geophysics", "Science"]}, "OL9636287W": {"goodreads": "7320961", "isbn_10": "0920486495", "isbn_13": "9780920486498", "title": "wake", "number_of_pages": 288, "publish_date": "September 16, 2003", "covers": [2686492], "subjects": ["Canadian", "Poetry", "History - General History", "Poetry / Canadian", "Single Author", "Canada - General"]}, "OL9636536W": {"goodreads": "6434947", "isbn_10": "0920763502", "isbn_13": "9780920763506", "title": "Earle Birney", "number_of_pages": 47, "publish_date": "June 1983", "subjects": ["Bibliographies, catalogues, discographies", "General", "Literature - Classics / Criticism"]}, "OL9637397W": {"isbn_10": "0922152446", "isbn_13": "9780922152445", "title": "GeoRef Thesaurus", "number_of_pages": 842, "publish_date": "October 1998", "covers": [12530168], "subjects": ["Earth Sciences - Geology", "Science"]}, "OL9638088W": {"isbn_10": "0924677287", "isbn_13": "9780924677281", "title": "Turbocad Designer", "publish_date": "April 1995", "subjects": ["Software - Productivity - CDROM / PC"]}, "OL9638168W": {"goodreads": "5103902", "isbn_10": "0925133523", "isbn_13": "9780925133526", "title": "Human Care Services Directory of Metropolitan Chicago 1999 (Human Care Services Directory of Metropolitan Chicago)", "number_of_pages": 700, "publish_date": "December 1998", "subjects": ["Directories", "Reference"]}, "OL9639136W": {"goodreads": "1725299", "isbn_10": "0826217605", "isbn_13": "9780826217608", "title": "Uncovering the Constitution's Moral Design", "number_of_pages": 328, "publish_date": "October 28, 2007", "covers": [2657577], "subjects": ["Constitutional law", "History / United States", "Political", "Political science & theory", "Methodology", "Moral and ethical aspects", "Philosophy", "Constitution: government & the state", "United States", "Constitutional", "Political Science", "Politics/International Relations", "USA", "Constitutional & administrative law", "Constitutions", "Legal Reference / Law Profession", "Practical & applied ethics"]}, "OL9639883W": {"isbn_10": "0827442939", "isbn_13": "9780827442931", "title": "Famous Women of Yesterday and Today", "publish_date": "June 1977", "subjects": []}, "OL9642646W": {"goodreads": "5985514", "isbn_10": "0828900906", "isbn_13": "9780828900904", "title": "Benjamin Franklin", "publish_date": "1969", "subjects": ["Franklin, Benjamin", "Drama"]}, "OL9643426W": {"goodreads": "2434662", "isbn_10": "0830902562", "isbn_13": "9780830902569", "title": "Emma Smith", "publish_date": "June 1954", "subjects": []}, "OL9644522W": {"goodreads": "3160911", "isbn_10": "092929341X", "isbn_13": "9780929293417", "title": "Domestic violence in Nepal", "publish_date": "1998", "covers": [13863396], "subjects": ["Law and legislation", "Nepal", "Family violence"]}, "OL9644615W": {"isbn_10": "0929387295", "isbn_13": "9780929387291", "title": "Official Chicago Cubs, 1992 Daily Planner", "publish_date": "October 1991", "subjects": ["Sports & Recreation", "General"]}, "OL9645318W": {"isbn_10": "0929991109", "isbn_13": "9780929991108", "title": "Faza Car Graphic Abarth Guide", "number_of_pages": 456, "publish_date": "June 1, 1984", "covers": [6294600, 6294599], "subjects": ["Religion"]}, "OL9645341W": {"isbn_10": "0930016173", "isbn_13": "9780930016173", "title": "Philippines Guide", "publish_date": "December 1992", "subjects": ["Travel"]}, "OL9645402W": {"goodreads": "3343298", "isbn_10": "0930042115", "isbn_13": "9780930042110", "title": "Aesthetic Function", "publish_date": "June 1970", "subjects": ["Literary theory"]}, "OL9645938W": {"isbn_10": "0930528042", "isbn_13": "9780930528041", "title": "The midnight snack cookbook", "number_of_pages": 100, "publish_date": "1982", "subjects": ["Snack foods"]}, "OL9646660W": {"isbn_10": "0931286026", "isbn_13": "9780931286025", "title": "On record, 11 artists 1963", "publish_date": "1981", "subjects": ["Interviews", "Pop art", "Artists", "United States"]}, "OL9646685W": {"isbn_10": "0931299446", "isbn_13": "9780931299445", "title": "Orange County 1994", "publish_date": "December 1994", "subjects": ["United States - General", "Travel - United States"]}, "OL9648290W": {"isbn_10": "0932828337", "isbn_13": "9780932828330", "title": "Pepo\u00cc\u0081n Osorio", "number_of_pages": 19, "publish_date": "1996", "subjects": ["Installations (Art)", "Puerto Rico", "Newark", "Osorio, Pepo\u00cc\u0081n", "Exhibitions", "Artists", "Badge of honor"]}, "OL9648405W": {"isbn_10": "0932897967", "isbn_13": "9780932897961", "title": "Mechanical Working & Steel Processing Conference", "number_of_pages": 596, "publish_date": "March 1995", "covers": [14436965], "subjects": ["Technology & Industrial Arts", "Construction - General"]}, "OL9648725W": {"isbn_10": "0933175132", "isbn_13": "9780933175136", "title": "Les grottes des crocodiles de Maabdah (Samoun): Un cas extre\u00cc\u0082me d'analyse arche\u00cc\u0081ologique (Varia aegyptiaca. Supplement)", "number_of_pages": 48, "publish_date": "1987", "subjects": ["Caves", "Antiquities", "El Ma\u00ca\u00bbabda (Egypt)", "El Ma\u00ca\u00bbabda"]}, "OL9649394W": {"isbn_10": "0933729197", "isbn_13": "9780933729193", "title": "Strategies in the War Against Drugs", "number_of_pages": 11, "publish_date": "1987", "subjects": []}, "OL9649572W": {"isbn_10": "0933885261", "isbn_13": "9780933885264", "title": "Site planning vignette preview", "number_of_pages": 65, "publish_date": "1997", "subjects": ["Certification", "Examinations, questions, etc", "Building sites", "Architects", "United States", "Architecture"]}, "OL9626321W": {"goodreads": "4170263", "isbn_10": "0832847305", "isbn_13": "9780832847301", "title": "Nippers, nightcaps and needles", "publish_date": "1995", "subjects": ["Charities", "Pigeon Cove Circle", "Local history", "Pigeon Cove (Mass.)", "Pigeon Cove", "Pigeon Cove Chapel", "Ann, Cape (Mass.)", "Rockport (Mass.)"]}, "OL9649835W": {"goodreads": "4166784", "isbn_10": "0832898716", "isbn_13": "9780832898716", "title": "Descendants of James Dyer & Jane Finn of Jackson County, Tennessee", "publish_date": "July 1999", "subjects": []}, "OL9650392W": {"isbn_10": "0834122464", "isbn_13": "9780834122468", "title": "What Does It Mean to Be Saved?", "number_of_pages": 88, "publish_date": "March 10, 2006", "covers": [2659870], "subjects": ["RELIGION / Christian Theology / General", "Christian Theology - Soteriology", "Religion", "Religion / Theology", "Religion - Theology", "Salvation", "Christian Theology - Systematic"]}, "OL9650836W": {"goodreads": "2084636", "isbn_10": "0835111067", "isbn_13": "9780835111065", "title": "English Chinese Dictionary of Abbreviation and Acronyms", "publish_date": "August 1980", "subjects": ["Reference"]}, "OL9651619W": {"isbn_10": "0836413032", "isbn_13": "9780836413038", "title": "Contributions to Indian Geography", "publish_date": "March 1985", "subjects": ["India", "Geography (General)", "Geography"]}, "OL9652135W": {"goodreads": "6622151", "isbn_10": "093411479X", "isbn_13": "9780934114790", "title": "Cajun Dictionary", "number_of_pages": 32, "publish_date": "June 1986", "subjects": ["General", "Reference"]}, "OL9652569W": {"goodreads": "296357", "isbn_10": "093446829X", "isbn_13": "9780934468299", "title": "Myth and Modern Man in Sherlock Holmes", "number_of_pages": 325, "publish_date": "August 1993", "subjects": ["Novels, other prose & writers: 19th century", "Literary Criticism", "English, Irish, Scottish, Welsh", "Nostalgia in literature", "Sherlock Holmes", "Doyle, Arthur Conan, 1859-1930", "Doyle, Arthur Conan,", "Holmes, Sherlock (Fictitious charcter)", "English", "Sir,", "Novels, other prose & writers: from c 1900 -", "Characters", "1859-1930", "Literature - Classics / Criticism"]}, "OL9653084W": {"isbn_10": "0934902003", "isbn_13": "9780934902007", "title": "Video reading technics", "publish_date": "1986", "subjects": ["Reading", "High interest-low vocabulary books", "Remedial teaching"]}, "OL9653270W": {"isbn_10": "0935037810", "isbn_13": "9780935037814", "title": "Mary Neumuth: No one spoke ", "number_of_pages": 51, "publish_date": "1998", "subjects": ["Exhibitions", "Neumuth, Mary"]}, "OL9654318W": {"isbn_10": "0935908684", "isbn_13": "9780935908688", "title": "Becoming Spiritual", "publish_date": "May 1990", "subjects": ["Self-Help"]}, "OL9654335W": {"goodreads": "6160570", "isbn_10": "0935912657", "isbn_13": "9780935912654", "title": "Official Directory of Connecticut Libraries and Media Centers, 1992", "number_of_pages": 250, "publish_date": "May 1996", "subjects": ["Teaching Methods & Materials - General", "Education / Teaching"]}, "OL9654608W": {"isbn_10": "0936164530", "isbn_13": "9780936164533", "title": "Patterns in HMO enrollment", "number_of_pages": 34, "publish_date": "1991", "subjects": ["Health Maintenance Organizations", "United States", "utilization", "Statistics"]}, "OL9655029W": {"goodreads": "2817586", "isbn_10": "093655617X", "isbn_13": "9780936556178", "title": "This Wanting to Sing", "publish_date": "August 1991", "subjects": ["20th century", "Brazilian Literature", "Asian authors", "Poetry", "Translations into English", "Latin American Poetry"]}, "OL9655212W": {"goodreads": "7167998", "isbn_10": "0936767952", "isbn_13": "9780936767956", "title": "Inside Microsoft Windows 95: Resource Guide, Volume 1", "number_of_pages": 261, "publish_date": "1997", "subjects": []}, "OL9655684W": {"isbn_10": "0937205125", "isbn_13": "9780937205129", "title": "Adventures in Violinland Bk. 1f", "number_of_pages": 88, "publish_date": "April 1994", "subjects": ["Musical Instruments - Strings", "Music"]}, "OL9655729W": {"isbn_10": "0937247553", "isbn_13": "9780937247556", "title": "Hands Across Michigan", "publish_date": "December 1996", "subjects": ["Art & Art Instruction", "General"]}, "OL9655809W": {"goodreads": "2217268", "isbn_10": "0937299936", "isbn_13": "9780937299937", "title": "No comment and other admissions of guilt (Briefly-- : perspectives on legislation, regulation, and litigation)", "number_of_pages": 25, "publish_date": "2000", "covers": [5142097], "subjects": ["Public relations", "Mass media and business", "United States"]}, "OL9656823W": {"goodreads": "743578", "isbn_10": "0938293508", "isbn_13": "9780938293507", "title": "How to Coach Winning Soccer", "publish_date": "June 1987", "covers": [5142374], "subjects": ["Soccer", "Sports & Recreation"]}, "OL9656986W": {"isbn_10": "0938464094", "isbn_13": "9780938464099", "title": "Short Shots", "publish_date": "June 1982", "subjects": []}, "OL9657187W": {"isbn_10": "0938625292", "isbn_13": "9780938625292", "title": "Where were the women?", "number_of_pages": 12, "publish_date": "1990", "subjects": ["United States", "Women in literature", "History", "Women", "Drama"]}, "OL9657388W": {"isbn_10": "0938744763", "isbn_13": "9780938744764", "title": "Birth Environments", "number_of_pages": 110, "publish_date": "June 1991", "subjects": ["Architecture", "Politics - Current Events", "Public Policy - Social Services & Welfare"]}, "OL9657421W": {"goodreads": "4813621", "isbn_10": "0938772031", "isbn_13": "9780938772033", "title": "Dawn upon the Kosmos", "publish_date": "December 1983", "subjects": []}, "OL9657486W": {"goodreads": "6359668", "isbn_10": "093886291X", "isbn_13": "9780938862918", "title": "Expert Systems and Artificial Intelligence", "number_of_pages": 350, "publish_date": "July 1987", "subjects": ["Computer Bks - General Information", "Expert Systems", "Artificial Intelligence", "Artificial Intelligence - General", "Computer Books: Operating Systems", "Expert systems (Computer science)"]}, "OL9659249W": {"goodreads": "4398230", "isbn_10": "0838587437", "isbn_13": "9780838587430", "title": "Surgery Annual 1991 Part 1", "number_of_pages": 650, "publish_date": "February 1, 1992", "subjects": ["Medical / Nursing", "Science/Mathematics", "Surgery", "Reference"]}, "OL9659518W": {"isbn_10": "0838969577", "isbn_13": "9780838969571", "title": "Career Perceptions of American Librarians", "publish_date": "June 1984", "subjects": []}, "OL9660156W": {"isbn_10": "0840325797", "isbn_13": "9780840325792", "title": "About biology", "number_of_pages": 97, "publish_date": "1981", "subjects": ["Laboratory manuals", "Biology"]}, "OL9660598W": {"isbn_10": "0840347057", "isbn_13": "9780840347053", "title": "Speech 100 Student Handbook", "number_of_pages": 32, "publish_date": "February 1, 1988", "subjects": ["PUBLIC SPEAKING", "Language Arts & Disciplines / Public Speaking"]}, "OL9660644W": {"isbn_10": "0840349149", "isbn_13": "9780840349149", "title": "Performance of literature in the classroom", "number_of_pages": 74, "publish_date": "1988", "subjects": ["Study and teaching", "Oral interpretation"]}, "OL9660900W": {"isbn_10": "0840359314", "isbn_13": "9780840359315", "title": "Business and Public Issues", "number_of_pages": 96, "publish_date": "May 1, 1990", "subjects": ["Business & Economics / Government & Business", "State And Business", "General", "Business / Economics / Finance", "BUSINESS AND POLITICS", "Business/Economics"]}, "OL9661223W": {"isbn_10": "0840373716", "isbn_13": "9780840373717", "title": "Fundamentals of Speech Communications", "publish_date": "December 1990", "subjects": ["Science/Mathematics"]}, "OL9661564W": {"isbn_10": "0840394780", "isbn_13": "9780840394781", "title": "Organic Evolution", "number_of_pages": 200, "publish_date": "May 1, 1994", "subjects": ["Organic Evolution", "Science/Mathematics", "Science / Chemistry / Organic", "ORGANIC COMPOUNDS"]}, "OL9661892W": {"isbn_10": "0841605866", "isbn_13": "9780841605862", "title": "Austria: Euro - Regional Map 1", "publish_date": "June 1997", "covers": [5143696], "subjects": ["Maps & Road Atlases", "Europe - Austria", "Travel - Foreign", "Travel", "Reference - General", "Maps"]}, "OL9662105W": {"goodreads": "7090324", "isbn_10": "0842319638", "isbn_13": "9780842319638", "title": "Josh Carter and the Black Forest Mystery", "number_of_pages": 160, "publish_date": "December 1984", "covers": [13272611], "subjects": ["Fiction - Mystery/ Detective", "Mystery & Detective - General"]}, "OL9663060W": {"isbn_10": "093939300X", "isbn_13": "9780939393008", "title": "IBHR", "publish_date": "1987", "subjects": ["Artists' books"]}, "OL9663085W": {"isbn_10": "0939430177", "isbn_13": "9780939430178", "title": "Scanner Master Florida Communications Guide", "publish_date": "May 1993", "subjects": ["General", "Reference", "Radio Broadcasting"]}, "OL9663460W": {"isbn_10": "0939738287", "isbn_13": "9780939738281", "title": "The Treatment of the Jews in the Christian Writers of the First Three Centuries (Treatment of the Jews in the Christian Writers of the First)", "number_of_pages": 255, "publish_date": "May 1983", "subjects": ["Christianity - History - General", "Religion - Church History"]}, "OL9663473W": {"goodreads": "3250108", "isbn_10": "0939748622", "title": "Alpine Karst (2004, Volume 1)", "number_of_pages": 130, "publish_date": "2004", "subjects": []}, "OL9663504W": {"goodreads": "2922049", "isbn_10": "0939789043", "isbn_13": "9780939789047", "title": "Lower Extremity Reconstruction", "number_of_pages": 246, "publish_date": "December 1987", "subjects": ["Electromagnetism", "Science/Mathematics", "Science", "Science: General Issues"]}, "OL9663794W": {"isbn_10": "0940030802", "isbn_13": "9780940030800", "title": "Proceedings Of The Eleventh Conversation In Biomolecular Stereodynamics, Volume 1", "number_of_pages": 188, "publish_date": "2000", "covers": [5144196], "subjects": ["Science/Mathematics", "Congresses", "Science", "Biomolecules", "Life Sciences - Biochemistry", "Stereochemistry", "Macromolecules", "Molecular dynamics"]}, "OL9663850W": {"goodreads": "1284179", "isbn_10": "0940118130", "isbn_13": "9780940118133", "title": "The Book Esther (Torah Anthology)", "publish_date": "December 1978", "subjects": ["Religion"]}, "OL9664223W": {"isbn_10": "094038907X", "isbn_13": "9780940389076", "title": "Dickson County marriages", "publish_date": "2002", "subjects": ["Sources", "Registers of births, etc", "Marriage records", "Dickson County", "Dickson County (Tenn.)"]}, "OL9664711W": {"goodreads": "2209350", "isbn_10": "094088481X", "isbn_13": "9780940884816", "title": "On the emergence of \"Cthulhu\" & other observations", "number_of_pages": 72, "publish_date": "1995", "covers": [5144369], "subjects": ["Lovecraft, H. P", "Criticism and interpretation"]}, "OL9664845W": {"isbn_10": "0941037754", "isbn_13": "9780941037754", "title": "Hillel", "number_of_pages": 120, "publish_date": "December 2002", "subjects": ["Religion", "Religion - Theology", "General encyclopaedias", "Reference", "Christian Theology - General"]}, "OL9665024W": {"isbn_10": "0941214370", "isbn_13": "9780941214377", "title": "Diary of Brigham Young, 1857", "publish_date": "June 1980", "subjects": ["Reference"]}, "OL9665507W": {"isbn_10": "0941677591", "isbn_13": "9780941677592", "title": "A Garden of Music", "number_of_pages": 160, "publish_date": "June 1, 2003", "covers": [2691274], "subjects": ["Genres & Styles - Folk & Traditional", "Music", "Music/Songbooks", "Reference", "Folk & Traditional", "Audio Adult: Other"]}, "OL9665675W": {"isbn_10": "0941837009", "isbn_13": "9780941837002", "title": "Profiles in Management", "publish_date": "May 1987", "subjects": ["Business/Economics"]}, "OL9665731W": {"goodreads": "6292098", "isbn_10": "0941934764", "isbn_13": "9780941934763", "title": "State intervention in African family relations in post-colonial Africa (Twenty-second annual Hans Wolff memorial lecture, April 4, 1997)", "number_of_pages": 19, "publish_date": "1997", "covers": [5144664], "subjects": ["Family", "Politics and government", "Domestic relations", "1960-", "Africa"]}, "OL9665831W": {"goodreads": "4023371", "isbn_10": "0942035542", "isbn_13": "9780942035544", "title": "Steam locomotives of the Kansas City Southern", "number_of_pages": 48, "publish_date": "2000", "subjects": ["Kansas", "Pictorial works", "History", "Steam Locomotives", "Kansas City Southern Railway Company"]}, "OL9665964W": {"isbn_10": "0942211014", "isbn_13": "9780942211016", "title": "April Tragedy the Assassination of Abraham Lincoln", "number_of_pages": 216, "publish_date": "June 1988", "subjects": ["Biography / Autobiography", "Presidents & Heads of State"]}, "OL9666273W": {"goodreads": "5617366", "isbn_10": "0942511077", "isbn_13": "9780942511079", "title": "On Doing Less Harm", "number_of_pages": 265, "publish_date": "July 1988", "covers": [2691480], "subjects": ["Legal Reference / Law Profession", "Penology", "Jurisprudence"]}, "OL9666373W": {"goodreads": "6485189", "isbn_10": "0942633024", "isbn_13": "9780942633023", "title": "The flame still burns", "publish_date": "1989", "subjects": ["History", "20th century", "Louisiana", "Pentecostals"]}, "OL9666919W": {"isbn_10": "0943231884", "isbn_13": "9780943231884", "title": "Kiosk 95", "publish_date": "January 1920", "subjects": []}, "OL9667416W": {"isbn_10": "0943688191", "isbn_13": "9780943688190", "title": "Seser Hakdamot (Hebrew)", "publish_date": "June 1988", "subjects": []}, "OL9668457W": {"goodreads": "6259483", "isbn_10": "084428906X", "isbn_13": "9780844289069", "title": "Essential Austria (1996)", "publish_date": "June 1996", "subjects": ["Europe - Austria", "Travel - Foreign", "Austria", "Travel", "Sociology, Social Studies"]}, "OL9668514W": {"isbn_10": "0844410098", "isbn_13": "9780844410098", "title": "Sched E-f 2000", "publish_date": "January 2000", "subjects": ["Reference", "Catalogs"]}, "OL9668634W": {"goodreads": "4094460", "isbn_10": "0844610402", "isbn_13": "9780844610405", "title": "Donnes Influence in English Literature", "publish_date": "June 1932", "subjects": []}, "OL9669519W": {"isbn_10": "0846702274", "isbn_13": "9780846702276", "title": "Plains Indians of North America (Butterfly Books)", "publish_date": "1976", "subjects": ["Indians of North America", "Culture", "Juvenile literature"]}, "OL9669931W": {"goodreads": "3390946", "isbn_10": "0848800052", "isbn_13": "9780848800055", "title": "Charles C. DeRudio", "publish_date": "1983", "subjects": ["1866-1895", "DeRudio, Charles Camilus", "United States", "Army", "Indians of North America", "Wars", "Little Bighorn, Battle of the, Mont., 1876"]}, "OL9670154W": {"goodreads": "4074941", "isbn_10": "0849309689", "isbn_13": "9780849309687", "title": "Managing Cisco Network Security", "number_of_pages": 512, "publish_date": "September 15, 2001", "subjects": ["Networking - General", "Computer Books: General", "Security - General", "Computing and Information Technology", "Computer Communications & Networking", "Computers - Communications / Networking", "Computers", "Data security & data encryption"]}, "OL9670340W": {"goodreads": "2023241", "isbn_10": "0849340691", "isbn_13": "9780849340697", "title": "Clean-in-Place for Biopharmaceutical Processes (Drugs and the Pharmaceutical Sciences)", "number_of_pages": 416, "publish_date": "October 15, 2007", "covers": [2663777], "subjects": ["Equipment and supplies", "Pharmacology", "Medical", "Medical / Pharmacology", "Cleaning", "Drugs", "Pharmaceutical technology", "Sterilization", "Clean rooms", "Medical / Nursing"]}, "OL9670930W": {"goodreads": "6136096", "isbn_10": "0849958296", "isbn_13": "9780849958298", "title": "The First Christmas CD-ROM", "publish_date": "November 18, 1997", "subjects": ["Religion - Biblical Stories", "Juvenile Nonfiction", "Holidays & Celebrations - Christmas & Advent", "Software - Children Ages 4-8 - CDROM / Universal", "Holidays & Festivals - Christmas", "Religion - Bible - Stories", "Juvenile Fiction / Holidays & Festivals / Christmas", "Children: Grades 4-6"]}, "OL9671859W": {"isbn_10": "0944433146", "isbn_13": "9780944433140", "title": "The Almanac of Seapower 1995", "number_of_pages": 311, "publish_date": "1995", "subjects": ["History - Military History"]}, "OL9672387W": {"isbn_10": "0944932002", "isbn_13": "9780944932001", "title": "Healing Where You Hurt...On the Inside", "publish_date": "1981", "subjects": []}, "OL9672667W": {"isbn_10": "0945282109", "isbn_13": "9780945282105", "title": "The Joseph Houle family of Forest County, Wisconsin", "number_of_pages": 396, "publish_date": "2000", "subjects": ["Family", "Houle family", "Genealogy", "Houle, Clara", "Forest County (Wis.)", "Houle, Joseph"]}, "OL9672813W": {"goodreads": "5447405", "isbn_10": "0945442173", "isbn_13": "9780945442172", "title": "Essential Computer Skills for Lifetime Career Success", "publish_date": "July 1995", "subjects": ["Computer Books: General"]}, "OL9674158W": {"isbn_10": "0946621209", "isbn_13": "9780946621200", "title": "Understanding Islam and the Muslims", "number_of_pages": 32, "publish_date": "December 1998", "subjects": ["Islam - General", "Religion - World Religions"]}, "OL9674618W": {"isbn_10": "0946868077", "isbn_13": "9780946868070", "title": "The Saltire Scottish Song Book", "number_of_pages": 105, "publish_date": "December 1991", "subjects": ["Ethnic", "Music/Songbooks", "Folk music", "Scotland"]}, "OL9675461W": {"isbn_10": "0947795936", "isbn_13": "9780947795931", "title": "Fertility and the Family", "number_of_pages": 160, "publish_date": "March 1989", "covers": [13111314], "subjects": ["Population & demography", "Human Fertility", "Human biology", "Health/Fitness", "Human Reproduction"]}, "OL9677970W": {"isbn_10": "0950805033", "isbn_13": "9780950805030", "title": "Meditation", "number_of_pages": 128, "publish_date": "June 1989", "subjects": ["Religion"]}, "OL9678631W": {"goodreads": "2665919", "isbn_10": "0951471597", "isbn_13": "9780951471593", "title": "Call Us Back to Donegal", "number_of_pages": 52, "publish_date": "December 31, 2000", "subjects": ["History", "Transport: General Interest", "Trains & railways: general interest", "Ireland"]}, "OL9680115W": {"goodreads": "7027541", "isbn_10": "140010582X", "isbn_13": "9781400105823", "title": "House Lust", "publish_date": "January 1, 2008", "covers": [2733928], "subjects": ["Real Estate - General", "Business & Economics/Real Estate - General", "Social Science / Sociology / General", "General", "Unabridged Audio - Misc.Nonfiction", "House & Home/General", "Sociology", "Sociology - General", "Social Science", "Unabridged Audio / Misc.Nonfiction"]}, "OL9680124W": {"goodreads": "2820660", "isbn_10": "1400302196", "isbn_13": "9781400302192", "title": "Singing in the Pond", "number_of_pages": 6, "publish_date": "May 22, 2003", "covers": [2734019], "subjects": ["Children Audio", "Music - Christian", "Juvenile Fiction", "Religious - Christian", "Religion / General", "Children's Audio - Music", "Audio: Juvenile"]}, "OL9680308W": {"goodreads": "5471751", "isbn_10": "1401014933", "isbn_13": "9781401014933", "title": "The Sea's Lament", "number_of_pages": 256, "publish_date": "November 2001", "covers": [2734637], "subjects": ["Historical fiction", "Sea & Ocean", "Fiction", "Fiction - General", "Sea Stories", "Historical - General", "Modern fiction"]}, "OL9680362W": {"goodreads": "1048686", "isbn_10": "1401017681", "isbn_13": "9781401017682", "title": "Freedom, Festivals and Caste in Trinidad After Slavery", "number_of_pages": 348, "publish_date": "December 2000", "covers": [2734772], "subjects": ["History: American", "Caribbean islands", "Social History", "American history", "Caribbean & West Indies - General", "History", "Sociology"]}, "OL9680450W": {"isbn_10": "1401023754", "isbn_13": "9781401023751", "title": "The Sin of Loving", "number_of_pages": 521, "publish_date": "July 2003", "subjects": ["Fiction", "General & Literary Fiction", "Christian - General", "Religious - General", "Fiction - Religious"]}, "OL9680714W": {"isbn_10": "1401039685", "isbn_13": "9781401039684", "title": "Why Freedom", "number_of_pages": 252, "publish_date": "April 2002", "covers": [2735564], "subjects": ["Ethics & Moral Philosophy", "Free Will & Determinism", "Philosophy"]}, "OL9680847W": {"isbn_10": "1401048447", "isbn_13": "9781401048440", "title": "The Pilgrimage", "number_of_pages": 260, "publish_date": "May 2002", "covers": [2735897], "subjects": ["Short Stories (single author)", "Fiction", "Fiction - General", "Modern fiction", "Short stories"]}, "OL9681584W": {"isbn_10": "1401088821", "isbn_13": "9781401088828", "title": "The Bad Guys Are Winning", "number_of_pages": 212, "publish_date": "July 2003", "covers": [2737430], "subjects": ["Action & Adventure", "Fiction - General", "Fiction", "Adventure / thriller"]}, "OL9681664W": {"isbn_10": "1401093507", "isbn_13": "9781401093501", "title": "Towards Another God", "number_of_pages": 336, "publish_date": "April 2003", "covers": [2737559], "subjects": ["Religion - Socialissues", "General", "Religion: general", "Religion"]}, "OL9681847W": {"isbn_10": "1401810373", "isbn_13": "9781401810375", "title": "Wiring for Wireless Sites", "number_of_pages": 280, "publish_date": "September 9, 2002", "covers": [2738058], "subjects": ["Communications engineering / telecommunications", "Science/Mathematics", "Wiring;for;Wireless;Sites", "Engineering - Electrical & Electronic", "Telecommunications", "Electronics engineering", "Electricity", "Technology & Industrial Arts", "Technology & Engineering", "Technology / Engineering / Electrical", "Electronics - General"]}, "OL9682743W": {"isbn_10": "0850916690", "isbn_13": "9780850916690", "title": "For Better, for Worse, for Ever?", "number_of_pages": 172, "publish_date": "October 1995", "covers": [2664737], "subjects": ["Marriage", "Beauty & Grooming - General", "Family & Relationships", "Family/Marriage", "Love / Sex / Marriage", "Marriage, family & other relationships"]}, "OL9683704W": {"isbn_10": "0851707653", "isbn_13": "9780851707655", "title": "Media Courses Uk 2000", "number_of_pages": 262, "publish_date": "April 15, 2000", "covers": [2665316], "subjects": ["Education / Teaching", "Yearbooks, annuals, almanacs", "Curricula", "Film & Video - General", "Higher", "Performing Arts/Dance", "Media Studies", "Higher & further education", "United Kingdom, Great Britain", "Film studies", "Motion Picture Industry", "Mass Media - General", "Cinema industry", "Performing Arts", "College And University Curricula"]}, "OL9686748W": {"isbn_10": "0853648301", "isbn_13": "9780853648307", "title": "The Triumph of Christ in African Perspective (Paternoster Theological Monographs)", "number_of_pages": 450, "publish_date": "December 31, 1969", "covers": [2666843], "subjects": ["Africa", "Christian Life - Spiritual Growth", "Religion", "Christology"]}, "OL9686770W": {"isbn_10": "0853656371", "isbn_13": "9780853656371", "title": "Reading Therapy", "number_of_pages": 212, "publish_date": "December 1988", "covers": [11703614], "subjects": ["Teaching of those with special educational needs", "Reference", "Library Services For Specific Groups"]}, "OL9687372W": {"isbn_10": "0854394087", "isbn_13": "9780854394081", "title": "Good News of Jesus", "number_of_pages": 63, "publish_date": "December 1990", "subjects": ["Christianity - Theology - Christology", "Religion - Theology"]}, "OL9688815W": {"isbn_10": "0952217112", "isbn_13": "9780952217114", "title": "Thesaurus of Disability Index Terms", "number_of_pages": 84, "publish_date": "January 1996", "subjects": []}, "OL9691014W": {"goodreads": "725291", "isbn_10": "0953765717", "isbn_13": "9780953765713", "title": "The Shakespeare Chronicles: The Conspiracy of the Lancastrians", "number_of_pages": 318, "publish_date": "September 2000", "covers": [2695136], "subjects": ["History: World", "Ancient - General", "Historical fiction", "British & Irish history: c 1000 to c 1500", "True Stories", "English", "History", "England", "c 1000 CE to c 1500"]}, "OL9693633W": {"isbn_10": "0960127410", "isbn_13": "9780960127412", "title": "Teaching Strategies for Developing Intellectual Abilities", "publish_date": "June 1976", "subjects": []}, "OL9694388W": {"goodreads": "4308223", "isbn_10": "0960877436", "isbn_13": "9780960877430", "title": "Note by Note", "publish_date": "September 1989", "subjects": ["Music", "General", "Career/Job"]}, "OL9645040W": {"isbn_10": "0960969071", "isbn_13": "9780960969074", "title": "Badges and Distinctive Insignia of the Israeli Defense Forces", "publish_date": "June 1990", "subjects": []}, "OL9694577W": {"isbn_10": "0961025417", "isbn_13": "9780961025410", "title": "My Major is Philosophy (My Major is Philosophy)", "number_of_pages": 139, "publish_date": "July 1985", "covers": [11683667], "subjects": ["General", "Philosophy"]}, "OL9694689W": {"isbn_10": "0961148004", "isbn_13": "9780961148003", "title": "Home Stuff", "publish_date": "June 1982", "subjects": ["Education"]}, "OL9695100W": {"isbn_10": "0961407018", "isbn_13": "9780961407018", "title": "Physician Extraordinary", "publish_date": "June 1986", "subjects": ["Biography/Autobiography", "Biography / Autobiography", "Medical - General"]}, "OL9695572W": {"isbn_10": "0961590335", "isbn_13": "9780961590338", "title": "Tina's Science Adventures", "publish_date": "November 1992", "subjects": ["Children: Kindergarten"]}, "OL9695656W": {"isbn_10": "0961617403", "isbn_13": "9780961617400", "title": "Bird CDP Review Course", "number_of_pages": 300, "publish_date": "December 1989", "subjects": ["Nature / Field Guide Books", "Birds & Birdwatching - General"]}, "OL9696627W": {"isbn_10": "0962036234", "isbn_13": "9780962036231", "title": "The 1989 rookie baseball card digest", "number_of_pages": 67, "publish_date": "1989", "subjects": ["Baseball cards", "United States", "Collectors and collecting"]}, "OL9697449W": {"goodreads": "2802482", "isbn_10": "1402212925", "isbn_13": "9781402212925", "title": "Your Birthday, Your Card", "number_of_pages": 256, "publish_date": "June 1, 2008", "covers": [2740676], "subjects": ["Divination - Fortune Telling", "Body, Mind & Spirit / Fortune Telling", "Body, Mind & Spirit", "New Age", "New Age / Body, Mind & Spirit"]}, "OL9697807W": {"goodreads": "1648168", "isbn_10": "1403312788", "isbn_13": "9781403312785", "title": "Not Just Kid's Stuff", "number_of_pages": 108, "publish_date": "July 25, 2002", "covers": [2741621], "subjects": ["Short Stories (single author)", "Fiction", "Family & Relationships-Abuse - General", "Violence in society", "Fiction - General", "Fiction / Short Stories (single author)", "Abuse - General", "Coping with personal problems"]}, "OL9697932W": {"isbn_10": "1403322341", "isbn_13": "9781403322340", "title": "THE CRUSADE OF THE CHILDREN", "number_of_pages": 140, "publish_date": "August 5, 2002", "covers": [2741821], "subjects": ["Fiction", "General & Literary Fiction", "Christian - General", "Religious - General", "Fiction - Religious"]}, "OL9698751W": {"isbn_10": "1403383405", "isbn_13": "9781403383402", "title": "Succubi", "number_of_pages": 476, "publish_date": "January 21, 2003", "covers": [2743255], "subjects": ["Fiction", "Fiction / Psychological", "General & Literary Fiction", "Fiction - Psychological Suspense", "Psychological"]}, "OL9698844W": {"isbn_10": "1403389357", "isbn_13": "9781403389350", "title": "Bible and Inspirational Poetry", "number_of_pages": 108, "publish_date": "February 2003", "covers": [2743382], "subjects": ["Poetry texts & anthologies", "Inspirational & Religious", "Poetry"]}, "OL9698885W": {"isbn_10": "1403392250", "isbn_13": "9781403392251", "title": "Scrappy", "number_of_pages": 112, "publish_date": "January 30, 2003", "covers": [2743436], "subjects": ["Biography: general", "Biography / Autobiography", "Biography/Autobiography", "Parental Memoirs"]}, "OL9698969W": {"isbn_10": "1403398933", "isbn_13": "9781403398932", "title": "Jesus and Reincarnation", "number_of_pages": 240, "publish_date": "January 2003", "covers": [2743569], "subjects": ["Christian theology", "Christianity - Theology - General", "Religion - Theology", "Christian Theology - General"]}, "OL9699342W": {"goodreads": "6283442", "isbn_10": "1403973202", "isbn_13": "9781403973207", "title": "New Women Dramatists in America, 1890-1920", "number_of_pages": 288, "publish_date": "December 26, 2007", "covers": [2744893], "subjects": ["Women and literature", "Biography", "History and criticism", "Women dramatists, American", "American", "Literary Criticism", "American drama", "19th century", "United States", "Women Authors", "Literary Criticism & Collections / Women Authors", "Plays / Drama", "History", "Theatre, drama", "Literature - Classics / Criticism"]}, "OL9699350W": {"isbn_10": "1403975213", "isbn_13": "9781403975218", "title": "Global Communication and Transnational Public Spheres", "number_of_pages": 256, "publish_date": "February 5, 2008", "covers": [2744911], "subjects": ["Computers - General Information", "Communication, International", "Social aspects", "History & Theory - General", "Political Science / International Relations", "Political Science", "Politics/International Relations", "Information Technology", "International Relations - General", "International cooperation", "Telecommunication"]}, "OL9699491W": {"goodreads": "904367", "isbn_10": "1404219951", "isbn_13": "9781404219953", "title": "Negative Body Image (Danger Zone: Dieting and Eating Disorders)", "number_of_pages": 64, "publish_date": "June 30, 2007", "covers": [5151032], "subjects": ["Juvenile Nonfiction", "Body image in adolescence", "Eating disorders in adolescence", "Health Sciences (Young Adult)", "Self-perception", "General", "Children's Books/Ages 9-12 Fiction", "Children: Young Adult (Gr. 7-9)", "Health & Daily Living - General", "Juvenile literature"]}, "OL9699556W": {"goodreads": "6270493", "isbn_10": "1404241663", "isbn_13": "9781404241664", "title": "Sloths (Paws and Claws)", "number_of_pages": 24, "publish_date": "January 30, 2008", "covers": [2745636], "subjects": ["Juvenile Nonfiction", "Children: Grades 2-3", "Animals", "Animals - General", "Mammals"]}, "OL9699583W": {"isbn_10": "1404314571", "isbn_13": "9781404314573", "title": "A Lady's Visit to the Gold Diggings of Australia in 1852-53", "number_of_pages": 144, "publish_date": "October 2001", "covers": [2746465], "subjects": ["Fiction", "General & Literary Fiction", "Fiction - General", "General", "Modern fiction"]}, "OL9699805W": {"isbn_10": "1405123710", "isbn_13": "9781405123716", "title": "Barley", "number_of_pages": 416, "publish_date": "August 1, 2008", "subjects": ["Botany & plant sciences", "Science/Mathematics", "Nature / Plants", "Agriculture & Farming", "Technology", "Plants - Grasses", "BARLEY", "Nature", "Food Science"]}, "OL9699906W": {"isbn_10": "1405156473", "isbn_13": "9781405156479", "title": "The Young Athlete", "number_of_pages": 512, "publish_date": "November 28, 2007", "covers": [2750264], "subjects": ["Sports injuries & medicine", "Medical", "Pediatrics", "Sports & Recreation", "Training", "Medical / Sports Medicine", "Sports Medicine", "Adolescent", "Pediatric sports medicine", "Encyclopedias"]}, "OL9663560W": {"goodreads": "1265804", "isbn_10": "0862413036", "isbn_13": "9780862413033", "title": "Where the Clock Stands Still", "number_of_pages": 128, "publish_date": "October 1990", "covers": [12906373], "subjects": ["Fife (Scotland)", "Places & peoples: general interest", "Fife", "Travel - Foreign", "Pictorial works", "Photography", "Collections Of Photographs", "Travel", "Social life and customs", "Photographs: collections", "Scotland", "Europe - Great Britain - General"]}, "OL9681168W": {"isbn_10": "1413491553", "isbn_13": "9781413491555", "title": "Emotions", "number_of_pages": 128, "publish_date": "February 24, 2006", "covers": [2775260], "subjects": ["Poetry", "Poetry texts & anthologies", "General", "Poetry / General", "American - General"]}, "OL9627755W": {"isbn_10": "1414203179", "isbn_13": "9781414203171", "title": "The Biography of a Rabbit", "number_of_pages": 132, "publish_date": "October 2003", "covers": [2780195], "subjects": ["Fiction - General", "General", "General & Literary Fiction"]}, "OL9630088W": {"isbn_10": "1419609831", "isbn_13": "9781419609831", "title": "Tropical Communism", "number_of_pages": 370, "publish_date": "August 15, 2005", "covers": [2797406], "subjects": ["Eduardo Gonz\u00e1lez", "Current Events / International", "Biography & Autobiography / General"]}, "OL9686902W": {"goodreads": "930286", "isbn_10": "0978866525", "isbn_13": "9780978866525", "title": "Mostly True", "number_of_pages": 96, "publish_date": "September 15, 2007", "subjects": ["United States - General", "hobo; graffiti; cometbus", "Art & Art Instruction", "Popular Culture - General", "Art / Popular Culture", "Art", "Sociology - General"]}, "OL9677730W": {"isbn_10": "1435324781", "isbn_13": "9781435324787", "title": "The Lost Naval Papers", "number_of_pages": 200, "publish_date": "August 9, 2007", "covers": [2898424], "subjects": ["Fiction / General", "Literary", "General & Literary Fiction", "Fiction - General"]}, "OL9699759W": {"isbn_10": "1856571033", "isbn_13": "9781856571036", "title": "The Deadly Ambition", "number_of_pages": 236, "publish_date": "March 30, 2006", "covers": [3006988], "subjects": ["Fiction - General", "General", "Fiction", "Literary"]}, "OL9632908W": {"isbn_10": "1551972913", "isbn_13": "9781551972916", "title": "Countdown to Atlanta", "number_of_pages": 317, "publish_date": "May 1996", "covers": [2904149], "subjects": ["Fiction", "Thrillers", "Fiction - General", "Modern fiction", "General"]}, "OL9685701W": {"isbn_10": "1860580912", "isbn_13": "9781860580918", "title": "Fluid Sealing", "number_of_pages": 554, "publish_date": "March 13, 1997", "covers": [3014459], "subjects": ["Science/Mathematics", "Science / Mechanics", "Science", "Hydraulic engineering", "Mechanics - General"]}, "OL9671543W": {"isbn_10": "1933002131", "isbn_13": "9781933002132", "title": "Mom and the Polka-Dot Boo-Boo", "number_of_pages": 24, "publish_date": "2005-08-10", "covers": [3060908], "subjects": ["Children: Kindergarten", "General", "Juvenile Fiction", "Health & Daily Living - Diseases", "Children's Books/Ages 4-8 Fiction"]}, "OL9621958W": {"isbn_10": "3906769267", "isbn_13": "9783906769264", "title": "Is Human Life Special?", "number_of_pages": 290, "publish_date": "September 2002", "covers": [5417863, 5193451], "subjects": ["Religion - Commentaries / Reference", "Philosophy", "Ethics & Moral Philosophy", "Topics in philosophy", "Religious", "History", "Christian Theology - General"]}, "OL9623612W": {"goodreads": "628030", "isbn_10": "5553765498", "isbn_13": "9785553765491", "title": "Line of Fire-25.00", "publish_date": "January 1920", "subjects": []}, "OL9622436W": {"isbn_10": "3039105124", "isbn_13": "9783039105120", "title": "Kitsch And Kunst", "number_of_pages": 275, "publish_date": "May 17, 2005", "subjects": ["20th century", "Germany (West)", "History and criticism", "World War, 1939-1945", "Literary Criticism", "History - General History", "General", "German fiction", "Literature and the war", "European - German"]}, "OL9621837W": {"goodreads": "5967757", "isbn_10": "3631378661", "isbn_13": "9783631378663", "title": "Participatory Planning Of Sustainable Development Projects", "number_of_pages": 137, "publish_date": "August 2001", "covers": [5214823], "subjects": ["Development - General", "Business & Economics", "Business/Economics"]}, "OL9622801W": {"goodreads": "1397384", "isbn_10": "3631550960", "isbn_13": "9783631550960", "title": "Culture Matters", "number_of_pages": 166, "publish_date": "October 25, 2006", "covers": [3241942], "subjects": ["Literary Criticism", "American - Hispanic American"]}, "OL960130W": {"goodreads": "3694106", "isbn_10": "9282857247", "isbn_13": "9789282857243", "title": "Cycling", "number_of_pages": 59, "publish_date": "1999", "subjects": []}, "OL9665926W": {"goodreads": "6171906", "isbn_10": "8090274676", "isbn_13": "9788090274679", "title": "Capitano Ricco", "number_of_pages": 36, "publish_date": "December 2005", "covers": [3321916], "subjects": ["Children: Grades 2-3", "General", "Children's Books/Ages 4-8 Fiction", "Juvenile Fiction"]}, "OL9636272W": {"isbn_10": "0920474551", "title": "place called the Ridge", "number_of_pages": 223, "publish_date": "1989", "subjects": ["Ontario -- History -- 1791-1841 -- Fiction.", "Canadian fiction -- Women authors."]}, "OL9606485W": {"goodreads": "6533028", "isbn_10": "0413570509", "title": "Anvil of the heart", "number_of_pages": 312, "publish_date": "1985", "subjects": []}, "OL9674243W": {"isbn_10": "1873451113", "title": "Henry Moore Sculpture Fellow, Winchester School of Art, 1993", "publish_date": "1994", "subjects": ["Callan, Jonathan."]}, "OL9659559W": {"goodreads": "1542870", "isbn_10": "0838976891", "title": "Forming and funding public library foundations", "number_of_pages": 31, "publish_date": "1993", "covers": [11634005], "subjects": ["Charitable uses, trusts, and foundations.", "Library fund raising."]}, "OL9686508W": {"isbn_10": "0435967800", "title": "The rise of the authoritarian state in peripheral societies", "number_of_pages": 157, "publish_date": "1984", "subjects": ["Authoritarianism -- History -- 20th century."]}, "OL9645028W": {"goodreads": "7241584", "isbn_10": "0929752058", "title": "Mountain travel and rescue", "number_of_pages": 170, "publish_date": "1995", "genres": ["Handbooks, manuals, etc."], "subjects": ["Ski mountaineering -- Handbooks, manuals, etc", "Ski patrollers -- Handbooks, manuals, etc", "Mountaineering -- Search and rescue operations"]}, "OL9692818W": {"isbn_10": "0954727304", "title": "The tale of two shagging monkeys", "number_of_pages": 288, "publish_date": "2004", "genres": ["Fiction."], "subjects": ["Friendship -- Fiction.", "End of the world -- Fiction."]}, "OL9602710W": {"isbn_10": "0898246563", "title": "human community", "number_of_pages": 69, "publish_date": "1989", "subjects": ["Creative thinking", "Perception in children"]}, "OL9682768W": {"isbn_10": "1900510006", "title": "Solar heated timber drying kilns", "publish_date": "1996", "subjects": []}, "OL9615682W": {"isbn_10": "0900984554", "title": "Access denied", "number_of_pages": 18, "publish_date": "1997", "subjects": ["Homeless youth -- Services for -- Great Britain.", "Homeless youth -- Great Britain.", "Housing policy -- Great Britain."]}, "OL9678792W": {"isbn_10": "0903189143", "title": "Fine Art, A Selection of Paintings, Sculptures and Drawings by Royal Academicians, 1770-1980.", "number_of_pages": 100, "publish_date": "1985", "subjects": []}, "OL9602515W": {"isbn_10": "0898060575", "title": "Motivating people to work", "number_of_pages": 180, "publish_date": "1984", "subjects": ["Employee morale.", "Employee motivation.", "Motivation (Psychology)."]}, "OL9659589W": {"goodreads": "2264885", "isbn_10": "0838984312", "isbn_13": "9780838984314", "title": "Commemorating the past, celebrating the present, creating the future", "publish_date": "2007", "subjects": ["Technical services (Libraries) -- United States -- History", "Association for Library Collections & Technical Services -- History", "Technical services (Libraries) -- Forecasting"]}, "OL9674971W": {"isbn_10": "0947571604", "title": "Modelling snowmelt-induced processes", "number_of_pages": 380, "publish_date": "1986", "subjects": ["Thawing -- Mathematical models -- Congresses."]}, "OL9617333W": {"isbn_10": "0940733031", "title": "Decent intentions", "number_of_pages": 57, "publish_date": "1983", "subjects": []}, "OL9667727W": {"goodreads": "5010842", "isbn_10": "094396511X", "title": "In the child's best interest", "number_of_pages": 46, "publish_date": "1989", "subjects": ["Children's rights.", "United Nations. -- General Assembly."]}, "OL964162W": {"isbn_10": "9601205535", "title": "Urban transformations in the Balkans (1820-1920)", "number_of_pages": 137, "publish_date": "1996", "covers": [9474234], "subjects": ["Thessalonike\u0304 (Greece) -- Buildings, structures, etc."]}, "OL963294W": {"isbn_10": "3924040761", "title": "Jean Cocteau, der Zeichner =", "publish_date": "1989", "subjects": []}, "OL9683331W": {"goodreads": "2830705", "isbn_10": "1903688647", "isbn_13": "9781903688649", "title": "Belmore", "number_of_pages": 290, "publish_date": "2007", "covers": [5464766, 5464071, 5462549], "subjects": ["Coole Manor, Fermanagh, Ireland", "Corey family", "Lowry family"]}, "OL9615771W": {"isbn_10": "0907383513", "title": "3-D electromagnetic field analysis", "number_of_pages": 322, "publish_date": "1990", "genres": ["Congresses."], "covers": [5486231, 5124337], "subjects": ["Electromagnetic fields -- Congresses."]}, "OL9685836W": {"isbn_10": "0853081808", "title": "Individual voluntary arrangements", "number_of_pages": 262, "publish_date": "1992", "subjects": []}}